wsgi_monitor3.py
wsgi_monitor3-1.0.dist-info/DESCRIPTION.rst
wsgi_monitor3-1.0.dist-info/METADATA
wsgi_monitor3-1.0.dist-info/RECORD
wsgi_monitor3-1.0.dist-info/WHEEL
wsgi_monitor3-1.0.dist-info/metadata.json
wsgi_monitor3-1.0.dist-info/top_level.txt
