Metadata-Version: 2.0
Name: wsgi-monitor3
Version: 1.0
Summary: Auto-reload WSGI server when files change - Python 3
Home-page: https://github.com/flanaman/wsgi_monitor3
Author: Mark Flanagan
Author-email: mark.mflanagan@gmail.com
License: UNKNOWN
Download-URL: https://github.com/flanaman/wsgi_monitor3/archive/1.0.tar.gz
Platform: UNKNOWN
Classifier: Programming Language :: Python
Classifier: License :: OSI Approved :: Apache Software License
Classifier: Operating System :: OS Independent
Classifier: Framework :: Django
